chord/__init__.py
chord.py-0.0.1.dist-info/LICENSE
chord.py-0.0.1.dist-info/METADATA
chord.py-0.0.1.dist-info/WHEEL
chord.py-0.0.1.dist-info/top_level.txt
chord.py-0.0.1.dist-info/RECORD
