Metadata-Version: 2.1
Name: chord.py
Version: 0.0.1
Summary: A Python wrapper for the Discord API
Author-email: Agent0876 <shinseungmin070920@gmail.com>
License: MIT License        
Project-URL: Homepage, https://agent0876.xyz
Project-URL: Bug Tracker, https://github.com/chordpy/chord.py/issues
Classifier: Programming Language :: Python :: 3
Classifier: License :: OSI Approved :: MIT License
Classifier: Operating System :: OS Independent
Requires-Python: >=3.7
License-File: LICENSE
